spyql/__init__.py
spyql/agg.py
spyql/cli.py
spyql/log.py
spyql/nulltype.py
spyql/output_handler.py
spyql/parser.py
spyql/processor.py
spyql/prof.py
spyql/qdict.py
spyql/query.py
spyql/query_result.py
spyql/quotes_handler.py
spyql/sqlfuncs.py
spyql/utils.py
spyql/writer.py
spyql-0.9.0.dist-info/AUTHORS.rst
spyql-0.9.0.dist-info/LICENSE
spyql-0.9.0.dist-info/METADATA
spyql-0.9.0.dist-info/WHEEL
spyql-0.9.0.dist-info/entry_points.txt
spyql-0.9.0.dist-info/top_level.txt
spyql-0.9.0.dist-info/RECORD
