Metadata-Version: 2.1
Name: spyql
Version: 0.9.0
Summary: SPyQL: SQL with Python in the middle
Home-page: https://github.com/dcmoura/spyql
Author: Daniel C. Moura
Author-email: daniel.c.moura@gmail.com
License: MIT license
Project-URL: Documentation, https://spyql.readthedocs.io
Project-URL: Source, https://github.com/dcmoura/spyql
Keywords: sql data csv json
Classifier: Development Status :: 3 - Alpha
Classifier: Environment :: Console
Classifier: Intended Audience :: Developers
Classifier: License :: OSI Approved :: MIT License
Classifier: Natural Language :: English
Classifier: Programming Language :: Python :: 3
Classifier: Programming Language :: Python :: 3.6
Classifier: Programming Language :: Python :: 3.7
Classifier: Programming Language :: Python :: 3.8
Classifier: Programming Language :: Python :: 3.9
Classifier: Programming Language :: Python :: 3.10
Classifier: Topic :: Text Processing
Classifier: Topic :: Utilities
Requires-Python: >=3.6
License-File: LICENSE
License-File: AUTHORS.rst
Requires-Dist: Click (>=7.1.2)
Requires-Dist: asciichartpy
Requires-Dist: tabulate
